onep/__init__.py
onep/__main__.py
onep/colors.py
onep/commands/__init__.py
onep/commands/delete.py
onep/commands/document.py
onep/commands/edit.py
onep/commands/search.py
onep/commands/share.py
onep/commands/show.py
onep/commands/signin.py
onep/commands/vaults.py
onep/fields.py
onep/onep.py
onep/util.py
onep-0.6.1.dist-info/entry_points.txt
onep-0.6.1.dist-info/LICENSE
onep-0.6.1.dist-info/WHEEL
onep-0.6.1.dist-info/METADATA
onep-0.6.1.dist-info/RECORD
