Metadata-Version: 2.1
Name: onep
Version: 0.6.1
Summary: 1Password CLI helper
Home-page: https://github.com/apognu/1p
License: MIT
Keywords: password,1password,cli,secrets
Author: Antoine POPINEAU
Author-email: antoine@popineau.eu
Requires-Python: >=3.7
Classifier: License :: OSI Approved :: MIT License
Classifier: Programming Language :: Python :: 3
Classifier: Programming Language :: Python :: 3.10
Classifier: Programming Language :: Python :: 3.7
Classifier: Programming Language :: Python :: 3.8
Classifier: Programming Language :: Python :: 3.9
Classifier: Topic :: Security
Classifier: Topic :: Utilities
Requires-Dist: inquirer (>=2.9.2,<3.0.0)
Requires-Dist: keyring (>=23.5.0,<24.0.0)
Requires-Dist: phonenumbers (>=8.12.48,<9.0.0)
Requires-Dist: prettytable (>=3.3.0,<4.0.0)
Requires-Dist: termcolor (>=1.1.0,<2.0.0)
Requires-Dist: validators (>=0.19.0,<0.20.0)
Project-URL: Repository, https://github.com/apognu/1p
